ayaligo/__init__.py
ayaligo/components/__init__.py
ayaligo/context.py
ayaligo/frameworks/__init__.py
ayaligo/internal/board/__init__.py
ayaligo/internal/component/__init__.py
ayaligo/internal/framework/__init__.py
ayaligo/internal/protocol/__init__.py
ayaligo/platforms/__init__.py
ayaligo/protocols/__init__.py
ayaligo-0.0.0.dist-info/LICENSE
ayaligo-0.0.0.dist-info/METADATA
ayaligo-0.0.0.dist-info/WHEEL
ayaligo-0.0.0.dist-info/RECORD
